random_fields/__init__.py
random_fields/__version__.py
random_fields/generate_field.py
random_fields/utils.py
random_fields-1.0.1.dist-info/LICENSE
random_fields-1.0.1.dist-info/METADATA
random_fields-1.0.1.dist-info/WHEEL
random_fields-1.0.1.dist-info/top_level.txt
random_fields-1.0.1.dist-info/RECORD
