Metadata-Version: 2.2
Name: random_fields
Version: 1.0.1
Summary: Random fields on unstructured grids
Author: attr: random_fields.__author__
Classifier: Programming Language :: Python :: 3
Classifier: License :: OSI Approved :: BSD License
Classifier: Operating System :: Microsoft :: Windows
Classifier: Operating System :: Unix
Requires-Python: >=3.8
License-File: LICENSE
Requires-Dist: numpy>=2.0.2
Requires-Dist: matplotlib>=3.9.3
Requires-Dist: gstools>=1.6.0
Provides-Extra: testing
Requires-Dist: pytest>=7.4.2; extra == "testing"
Requires-Dist: pytest-cov>=4.1.0; extra == "testing"
Requires-Dist: tox>=4.4; extra == "testing"
Provides-Extra: docs
Requires-Dist: Sphinx==6.2.1; extra == "docs"
Requires-Dist: sphinx-rtd-theme==1.2.2; extra == "docs"
